mbf_heatmap/__init__.py
mbf_heatmap/chipseq/__init__.py
mbf_heatmap/chipseq/norm.py
mbf_heatmap/chipseq/order.py
mbf_heatmap/chipseq/plot_strategies.py
mbf_heatmap/chipseq/regions.py
mbf_heatmap/chipseq/smooth.py
mbf_heatmap/ddf/__init__.py
mbf_heatmap/ddf/heatmap.py
mbf_heatmap/ddf/norm.py
mbf_heatmap/ddf/order.py
mbf_heatmap/ddf/plot_strategies.py
mbf_heatmap-0.2.dist-info/AUTHORS.rst
mbf_heatmap-0.2.dist-info/LICENSE.txt
mbf_heatmap-0.2.dist-info/METADATA
mbf_heatmap-0.2.dist-info/WHEEL
mbf_heatmap-0.2.dist-info/top_level.txt
mbf_heatmap-0.2.dist-info/RECORD
