Metadata-Version: 2.1
Name: mbf-heatmap
Version: 0.2
Summary: swiss army heatmaps for delayed data frames and ChIPseq data
Home-page: https://github.com/TyberiusPrime/mbf_heatmap
Author: Florian Finkernagel
Author-email: finkernagel@imt.uni-marburg.de
License: mit
Platform: any
Classifier: Development Status :: 4 - Beta
Classifier: Programming Language :: Python
Requires-Python: >=3.6
Requires-Dist: matplotlib
Requires-Dist: mbf-align
Requires-Dist: mbf-genomics
Requires-Dist: numpy
Requires-Dist: pandas
Requires-Dist: pypipegraph
Requires-Dist: scipy
Provides-Extra: doc
Requires-Dist: numpydoc ; extra == 'doc'
Requires-Dist: sphinx ; extra == 'doc'
Requires-Dist: sphinx-bootstrap-theme ; extra == 'doc'
Provides-Extra: testing
Requires-Dist: mbf-align ; extra == 'testing'
Requires-Dist: mbf-genomics ; extra == 'testing'
Requires-Dist: mbf-qualitycontrol ; extra == 'testing'
Requires-Dist: mbf-sampledata ; extra == 'testing'
Requires-Dist: pytest ; extra == 'testing'
Requires-Dist: pytest-cov ; extra == 'testing'
Requires-Dist: pytest-icdiff ; extra == 'testing'
